{
    "py/object": "__main__.AreaOfStudy",
    "catalog": "2018-19",
    "degree": "Bachelor of Arts",
    "kind": "major",
    "name": "Exercise Science",
    "requirements": [
        {
            "py/object": "__main__.Requirement",
            "audited_by": null,
            "contract": false,
            "message": null,
            "name": "Core",
            "requirements": null,
            "result": {
                "py/object": "__main__.Rule",
                "rule": {
                    "py/object": "__main__.CountRule",
                    "count": 8,
                    "greedy": false,
                    "of": [
                        {
                            "py/object": "__main__.Rule",
                            "rule": {
                                "py/object": "__main__.CourseRule",
                                "course": "BIO 143"
                            }
                        },
                        {
                            "py/object": "__main__.Rule",
                            "rule": {
                                "py/object": "__main__.CourseRule",
                                "course": "BIO 243"
                            }
                        },
                        {
                            "py/object": "__main__.Rule",
                            "rule": {
                                "py/object": "__main__.CourseRule",
                                "course": "NURS 110"
                            }
                        },
                        {
                            "py/object": "__main__.Rule",
                            "rule": {
                                "py/object": "__main__.CourseRule",
                                "course": "ESTH 255"
                            }
                        },
                        {
                            "py/object": "__main__.Rule",
                            "rule": {
                                "py/object": "__main__.CourseRule",
                                "course": "ESTH 374"
                            }
                        },
                        {
                            "py/object": "__main__.Rule",
                            "rule": {
                                "py/object": "__main__.CourseRule",
                                "course": "ESTH 375"
                            }
                        },
                        {
                            "py/object": "__main__.Rule",
                            "rule": {
                                "py/object": "__main__.CourseRule",
                                "course": "ESTH 390"
                            }
                        },
                        {
                            "py/object": "__main__.Rule",
                            "rule": {
                                "py/object": "__main__.CourseRule",
                                "course": "PSYCH 125"
                            }
                        }
                    ]
                }
            },
            "save": null
        },
        {
            "py/object": "__main__.Requirement",
            "audited_by": null,
            "contract": false,
            "message": null,
            "name": "Electives",
            "requirements": null,
            "result": {
                "py/object": "__main__.Rule",
                "rule": {
                    "py/object": "__main__.CountRule",
                    "count": 2,
                    "greedy": false,
                    "of": [
                        {
                            "py/object": "__main__.Rule",
                            "rule": {
                                "py/object": "__main__.CourseRule",
                                "course": "BIO 247"
                            }
                        },
                        {
                            "py/object": "__main__.Rule",
                            "rule": {
                                "py/object": "__main__.CourseRule",
                                "course": "ESTH 295"
                            }
                        },
                        {
                            "py/object": "__main__.Rule",
                            "rule": {
                                "py/object": "__main__.CourseRule",
                                "course": "ESTH 373"
                            }
                        },
                        {
                            "py/object": "__main__.Rule",
                            "rule": {
                                "py/object": "__main__.CourseRule",
                                "course": "ESTH 376"
                            }
                        },
                        {
                            "py/object": "__main__.Rule",
                            "rule": {
                                "py/object": "__main__.CourseRule",
                                "course": "NEURO 239"
                            }
                        },
                        {
                            "py/object": "__main__.Rule",
                            "rule": {
                                "py/object": "__main__.CourseRule",
                                "course": "PSYCH 241"
                            }
                        },
                        {
                            "py/object": "__main__.Rule",
                            "rule": {
                                "py/object": "__main__.CourseRule",
                                "course": "PSYCH 247"
                            }
                        },
                        {
                            "py/object": "__main__.Rule",
                            "rule": {
                                "py/object": "__main__.CountRule",
                                "count": 1,
                                "greedy": false,
                                "of": [
                                    {
                                        "py/object": "__main__.Rule",
                                        "rule": {
                                            "py/object": "__main__.CourseRule",
                                            "course": "STAT 110"
                                        }
                                    },
                                    {
                                        "py/object": "__main__.Rule",
                                        "rule": {
                                            "py/object": "__main__.CourseRule",
                                            "course": "STAT 212"
                                        }
                                    },
                                    {
                                        "py/object": "__main__.Rule",
                                        "rule": {
                                            "py/object": "__main__.CourseRule",
                                            "course": "STAT 214"
                                        }
                                    }
                                ]
                            }
                        }
                    ]
                }
            },
            "save": null
        }
    ],
    "result": {
        "py/object": "__main__.Rule",
        "rule": {
            "py/object": "__main__.CountRule",
            "count": 2,
            "greedy": false,
            "of": [
                {
                    "py/object": "__main__.Rule",
                    "rule": {
                        "py/object": "__main__.ReferenceRule",
                        "requirement": "Core"
                    }
                },
                {
                    "py/object": "__main__.Rule",
                    "rule": {
                        "py/object": "__main__.ReferenceRule",
                        "requirement": "Electives"
                    }
                }
            ]
        }
    }
}